sphinx_docs_theme/__init__.py
sphinx_docs_theme/footer.html
sphinx_docs_theme/head.html
sphinx_docs_theme/layout.html
sphinx_docs_theme/navbar.html
sphinx_docs_theme/scripts.html
sphinx_docs_theme/theme.conf
sphinx_docs_theme/static/favicon.ico
sphinx_docs_theme/static/readme.txt
sphinx_docs_theme/static/css/common.css
sphinx_docs_theme/static/css/link.css
sphinx_docs_theme/static/css/style.min.css
sphinx_docs_theme/static/js/initializeHighlight.js
sphinx_docs_theme/static/lib/bootstrap/js/bootstrap.bundle.js
sphinx_docs_theme/static/lib/bootstrap/js/bootstrap.bundle.min.js
sphinx_docs_theme/static/lib/bootstrap/js/bootstrap.js
sphinx_docs_theme/static/lib/bootstrap/js/bootstrap.min.js
sphinx_docs_theme/static/lib/bootswatch/litera/bootstrap.css
sphinx_docs_theme/static/lib/bootswatch/litera/bootstrap.min.css
sphinx_docs_theme/static/lib/font-awesome/HELP-US-OUT.txt
sphinx_docs_theme/static/lib/font-awesome/README.md
sphinx_docs_theme/static/lib/font-awesome/package.json
sphinx_docs_theme/static/lib/font-awesome/css/font-awesome.css
sphinx_docs_theme/static/lib/font-awesome/css/font-awesome.css.map
sphinx_docs_theme/static/lib/font-awesome/css/font-awesome.min.css
sphinx_docs_theme/static/lib/font-awesome/fonts/FontAwesome.otf
sphinx_docs_theme/static/lib/font-awesome/fonts/fontawesome-webfont.eot
sphinx_docs_theme/static/lib/font-awesome/fonts/fontawesome-webfont.svg
sphinx_docs_theme/static/lib/font-awesome/fonts/fontawesome-webfont.ttf
sphinx_docs_theme/static/lib/font-awesome/fonts/fontawesome-webfont.woff
sphinx_docs_theme/static/lib/font-awesome/fonts/fontawesome-webfont.woff2
sphinx_docs_theme/static/lib/font-awesome/less/animated.less
sphinx_docs_theme/static/lib/font-awesome/less/bordered-pulled.less
sphinx_docs_theme/static/lib/font-awesome/less/core.less
sphinx_docs_theme/static/lib/font-awesome/less/fixed-width.less
sphinx_docs_theme/static/lib/font-awesome/less/font-awesome.less
sphinx_docs_theme/static/lib/font-awesome/less/icons.less
sphinx_docs_theme-1.0.7.dist-info/LICENSE
sphinx_docs_theme-1.0.7.dist-info/METADATA
sphinx_docs_theme-1.0.7.dist-info/WHEEL
sphinx_docs_theme-1.0.7.dist-info/top_level.txt
sphinx_docs_theme-1.0.7.dist-info/RECORD
