Metadata-Version: 2.1
Name: sphinx-docs-theme
Version: 1.0.7
Summary: Sphinx Theme for documentation sites.
Home-page: https://github.com/Bernardo-MG/sphinx-docs-theme
Author: Bernardo Martínez Garrido
Author-email: programming@bernardomg.com
License: MIT
Download-URL: https://github.com/Bernardo-MG/sphinx-docs-theme
Keywords: sphinx,theme,bootstrap,html5,python
Platform: any
Classifier: Development Status :: 5 - Production/Stable
Classifier: Framework :: Sphinx
Classifier: Framework :: Sphinx :: Theme
Classifier: Intended Audience :: Developers
Classifier: License :: OSI Approved :: MIT License
Classifier: Operating System :: OS Independent
Classifier: Programming Language :: Python
Classifier: Programming Language :: Python :: 3
Classifier: Programming Language :: Python :: 3.6
Classifier: Programming Language :: Python :: 3.7
Classifier: Programming Language :: Python :: 3.8
Classifier: Topic :: Documentation
Classifier: Topic :: Documentation :: Sphinx
Classifier: Topic :: Software Development :: Documentation
Requires-Python: >=3.6
Requires-Dist: Fabric
Requires-Dist: Sphinx
Requires-Dist: bernardomg.tox-test-command
Requires-Dist: bernardomg.version-extractor
Provides-Extra: test
Requires-Dist: tox ; extra == 'test'
